pycocoevalcap_cn/__init__.py
pycocoevalcap_cn/bleu/__init__.py
pycocoevalcap_cn/bleu/bleu.py
pycocoevalcap_cn/bleu/bleu_scorer.py
pycocoevalcap_cn/cider/__init__.py
pycocoevalcap_cn/cider/cider.py
pycocoevalcap_cn/cider/cider_scorer.py
pycocoevalcap_cn-0.0.1.dist-info/METADATA
pycocoevalcap_cn-0.0.1.dist-info/WHEEL
pycocoevalcap_cn-0.0.1.dist-info/licenses/LICENSE
pycocoevalcap_cn-0.0.1.dist-info/RECORD
